pysparkdt/__init__.py
pysparkdt/metastore.py
pysparkdt/spark_base.py
pysparkdt-1.1.0.dist-info/LICENSE
pysparkdt-1.1.0.dist-info/METADATA
pysparkdt-1.1.0.dist-info/WHEEL
pysparkdt-1.1.0.dist-info/RECORD
