Metadata-Version: 2.1
Name: pysparkdt
Version: 1.1.0
Summary: An open-source Python library for simplifying local testing of Databricks workflows that use PySpark and Delta tables.
Home-page: https://github.com/datamole-ai/pysparkdt
License: MIT
Author: Juraj Pall
Author-email: juraj.pall@datamole.ai
Requires-Python: >=3.8,<3.13
Classifier: License :: OSI Approved :: MIT License
Classifier: Programming Language :: Python :: 3
Classifier: Programming Language :: Python :: 3.8
Classifier: Programming Language :: Python :: 3.9
Classifier: Programming Language :: Python :: 3.10
Classifier: Programming Language :: Python :: 3.11
Classifier: Programming Language :: Python :: 3.12
Requires-Dist: delta-spark (>=3.0.0,<4.0.0)
Requires-Dist: numpy (<1.26.0) ; python_version >= "3.8" and python_version < "3.9"
Requires-Dist: numpy (>=1.26.0) ; python_version >= "3.9"
Requires-Dist: pyspark[sql] (>=3.5.0,<4.0.0)
Requires-Dist: setuptools (>=75.6.0,<76.0.0) ; python_version >= "3.12" and python_version < "3.13"
Project-URL: Repository, https://github.com/datamole-ai/pysparkdt
